seizhooks.py
seizhooks-0.0.1.dist-info/LICENSE
seizhooks-0.0.1.dist-info/METADATA
seizhooks-0.0.1.dist-info/WHEEL
seizhooks-0.0.1.dist-info/top_level.txt
seizhooks-0.0.1.dist-info/RECORD
