Metadata-Version: 2.1
Name: seizhooks
Version: 0.0.1
Summary: Seizhooks is a simple lib using discord api to interact with webhook
Author: uhq.s
Project-URL: Homepage, https://github.com/seized0/seizhooks
Project-URL: Issues, https://github.com/seized0/
Classifier: Programming Language :: Python :: 3
Classifier: License :: OSI Approved :: MIT License
Classifier: Operating System :: OS Independent
Requires-Python: >=3.9
License-File: LICENSE
